grok_mcp/__init__.py
grok_mcp/__main__.py
grok_mcp/config.py
grok_mcp/exceptions.py
grok_mcp/grok_client.py
grok_mcp/response_formatter.py
grok_mcp/search_tools.py
grok_mcp/server.py
grok_mcp-0.2.1.dist-info/METADATA
grok_mcp-0.2.1.dist-info/WHEEL
grok_mcp-0.2.1.dist-info/entry_points.txt
grok_mcp-0.2.1.dist-info/licenses/LICENSE
grok_mcp-0.2.1.dist-info/RECORD
