Metadata-Version: 2.4
Name: grok-mcp
Version: 0.2.1
Summary: MCP server for Grok X.com search integration using xAI API
Project-URL: Homepage, https://github.com/guzus/grok-mcp
Project-URL: Repository, https://github.com/guzus/grok-mcp
Project-URL: Issues, https://github.com/guzus/grok-mcp/issues
Author: guzus
License-Expression: MIT
License-File: LICENSE
Keywords: claude,grok,mcp,search,twitter,x.com,xai
Classifier: Development Status :: 4 - Beta
Classifier: Intended Audience :: Developers
Classifier: License :: OSI Approved :: MIT License
Classifier: Programming Language :: Python :: 3
Classifier: Programming Language :: Python :: 3.12
Classifier: Programming Language :: Python :: 3.13
Requires-Python: >=3.12
Requires-Dist: httpx>=0.27.0
Requires-Dist: mcp>=1.0.0
Requires-Dist: pydantic>=2.5.0
Requires-Dist: typing-extensions>=4.8.0
Provides-Extra: dev
Requires-Dist: black>=24.0.0; extra == 'dev'
Requires-Dist: mypy>=1.8.0; extra == 'dev'
Requires-Dist: pytest-asyncio>=0.23.0; extra == 'dev'
Requires-Dist: pytest-mock>=3.12.0; extra == 'dev'
Requires-Dist: pytest>=8.0.0; extra == 'dev'
Requires-Dist: ruff>=0.1.0; extra == 'dev'
